text2url/__init__.py
text2url/cli.py
text2url-0.1.0.dist-info/METADATA
text2url-0.1.0.dist-info/WHEEL
text2url-0.1.0.dist-info/entry_points.txt
text2url-0.1.0.dist-info/top_level.txt
text2url-0.1.0.dist-info/RECORD
